shorten/__init__.py
shorten/__version__.py
shorten/main.py
shorten/template.py
shorten_cli-0.1.data/scripts/shorten
shorten_cli-0.1.dist-info/DESCRIPTION.rst
shorten_cli-0.1.dist-info/METADATA
shorten_cli-0.1.dist-info/RECORD
shorten_cli-0.1.dist-info/WHEEL
shorten_cli-0.1.dist-info/metadata.json
shorten_cli-0.1.dist-info/top_level.txt
