Metadata-Version: 2.0
Name: shorten-cli
Version: 0.1
Summary: Simple (Python) tool to shorten any command in your terminal.
Home-page: https://github.com/Zsailer/shorten
Author: Zach Sailer
Author-email: zachsailer@gmail.com
License: MIT
Platform: UNKNOWN
Classifier: License :: OSI Approved :: MIT License
Classifier: Programming Language :: Python :: 3
Classifier: Programming Language :: Python :: 3.3
Classifier: Programming Language :: Python :: 3.4
Classifier: Programming Language :: Python :: 3.5
Classifier: Programming Language :: Python :: 3.6
Classifier: Programming Language :: Python :: Implementation :: CPython
Classifier: Programming Language :: Python :: Implementation :: PyPy
